askCO/__init__.py
askCO/tryCO.py
askco-1.0.2.dist-info/METADATA
askco-1.0.2.dist-info/WHEEL
askco-1.0.2.dist-info/top_level.txt
askco-1.0.2.dist-info/RECORD
