Metadata-Version: 2.4
Name: askCO
Version: 1.0.2
Summary: Python interface for Te Papa's collections API
Author-email: Lucy Schrader <lucy@schrader.nz>
License: MIT License
Project-URL: Homepage, https://github.com/lucyschrader/askCO
Keywords: python,museum,api
Classifier: Development Status :: 5 - Production/Stable
Classifier: License :: OSI Approved :: MIT License
Classifier: Intended Audience :: Education
Classifier: Programming Language :: Python :: 3
Classifier: Natural Language :: English
Requires-Python: >=3.11
Requires-Dist: requests
